python_mailable/__init__.py
python_mailable/mailable.py
python_mailable-0.1.0.dist-info/licenses/LICENSE
python_mailable-0.1.0.dist-info/METADATA
python_mailable-0.1.0.dist-info/WHEEL
python_mailable-0.1.0.dist-info/top_level.txt
python_mailable-0.1.0.dist-info/RECORD
