Metadata-Version: 2.4
Name: python-mailable
Version: 0.1.0
Summary: An expressive email builder for Python
Author: Brady Renting
Requires-Python: >=3.13
License-File: LICENSE
Dynamic: license-file
